{"filename":"correggio_mentreil_C.jpg","original":"http://localhost:8182/iiif/2/correggio_mentreil:masters:correggio_mentreil_C.jpg/full/full/0/default.jpg","pages":[{"regions":[{"bounding_box":{"fromX":882,"toX":1063,"fromY":47,"toY":71},"id":27689,"type":"title"},{"bounding_box":{"fromX":796,"toX":849,"fromY":48,"toY":70},"id":27686,"type":"title"},{"bounding_box":{"fromX":1078,"toX":1100,"fromY":55,"toY":75},"id":27691,"type":"text"},{"bounding_box":{"fromX":743,"toX":1120,"fromY":64,"toY":126},"id":27693,"type":"staff","symbols":[{"agnostic_symbol_type":"verticalLine","approximateX":743,"id":140743,"position_in_staff":"L1"},{"agnostic_symbol_type":"verticalLine","approximateX":758,"id":140744,"position_in_staff":"L1"},{"agnostic_symbol_type":"clef.G","approximateX":773,"id":140745,"position_in_staff":"L2"},{"agnostic_symbol_type":"metersign.Ct","approximateX":788,"id":140746,"position_in_staff":"L3"},{"agnostic_symbol_type":"note.whole","approximateX":803,"id":140747,"position_in_staff":"S4"},{"agnostic_symbol_type":"dot","approximateX":818,"id":140748,"position_in_staff":"S4"},{"agnostic_symbol_type":"note.half_up","approximateX":833,"id":140749,"position_in_staff":"S2"},{"agnostic_symbol_type":"note.whole","approximateX":848,"id":140750,"position_in_staff":"S4"},{"agnostic_symbol_type":"note.half_down","approximateX":863,"id":140751,"position_in_staff":"L5"},{"agnostic_symbol_type":"note.half_down","approximateX":878,"id":140752,"position_in_staff":"L5"},{"agnostic_symbol_type":"note.half_down","approximateX":893,"id":140753,"position_in_staff":"S4"},{"agnostic_symbol_type":"note.half_down","approximateX":908,"id":140754,"position_in_staff":"L5"},{"agnostic_symbol_type":"note.quarter_down","approximateX":923,"id":140755,"position_in_staff":"L4"},{"agnostic_symbol_type":"note.quarter_down","approximateX":938,"id":140756,"position_in_staff":"S3"},{"bounding_box":{"fromX":945,"toX":961,"fromY":64,"toY":96},"agnostic_symbol_type":"plica.up","id":346812,"position_in_staff":"L5"},{"bounding_box":{"fromX":948,"toX":964,"fromY":64,"toY":96},"agnostic_symbol_type":"lnote.rect","id":346813,"position_in_staff":"L5"},{"bounding_box":{"fromX":964,"toX":980,"fromY":64,"toY":96},"agnostic_symbol_type":"lnoteBlack.rect","id":346814,"position_in_staff":"S4"},{"agnostic_symbol_type":"note.eighth_down","approximateX":983,"id":140759,"position_in_staff":"L4"},{"agnostic_symbol_type":"note.eighth_down","approximateX":998,"id":140760,"position_in_staff":"S3"},{"agnostic_symbol_type":"note.half_down","approximateX":1013,"id":140761,"position_in_staff":"L4"},{"agnostic_symbol_type":"note.whole","approximateX":1028,"id":140762,"position_in_staff":"S4"},{"agnostic_symbol_type":"rest.whole","approximateX":1043,"id":140763,"position_in_staff":"L5"},{"agnostic_symbol_type":"note.whole","approximateX":1058,"id":140764,"position_in_staff":"S4"},{"agnostic_symbol_type":"dot","approximateX":1073,"id":140765,"position_in_staff":"S4"},{"agnostic_symbol_type":"note.half_up","approximateX":1088,"id":140766,"position_in_staff":"S2"},{"agnostic_symbol_type":"custos","approximateX":1103,"id":140767,"position_in_staff":"S4"}]},{"bounding_box":{"fromX":782,"toX":828,"fromY":122,"toY":143},"id":27700,"type":"lyrics"},{"bounding_box":{"fromX":830,"toX":969,"fromY":122,"toY":143},"id":27702,"type":"lyrics"},{"bounding_box":{"fromX":1010,"toX":1098,"fromY":124,"toY":145},"id":27703,"type":"lyrics"},{"bounding_box":{"fromX":641,"toX":1119,"fromY":145,"toY":193},"id":27696,"type":"staff","symbols":[{"agnostic_symbol_type":"clef.G","approximateX":641,"id":140768,"position_in_staff":"L2"},{"agnostic_symbol_type":"note.whole","approximateX":656,"id":140769,"position_in_staff":"S4"},{"agnostic_symbol_type":"note.half_down","approximateX":671,"id":140770,"position_in_staff":"L5"},{"agnostic_symbol_type":"note.half_down","approximateX":686,"id":140771,"position_in_staff":"L5"},{"agnostic_symbol_type":"note.half_down","approximateX":701,"id":140772,"position_in_staff":"S4"},{"agnostic_symbol_type":"note.half_down","approximateX":716,"id":140773,"position_in_staff":"S4"},{"agnostic_symbol_type":"note.half_down","approximateX":731,"id":140774,"position_in_staff":"L4"},{"agnostic_symbol_type":"note.half_down","approximateX":746,"id":140775,"position_in_staff":"S3"},{"agnostic_symbol_type":"note.whole","approximateX":761,"id":140776,"position_in_staff":"L3"},{"agnostic_symbol_type":"note.breve","approximateX":776,"id":140777,"position_in_staff":"S3"},{"agnostic_symbol_type":"rest.whole","approximateX":791,"id":140778,"position_in_staff":"L4"},{"agnostic_symbol_type":"rest.half","approximateX":806,"id":140779,"position_in_staff":"L3"},{"agnostic_symbol_type":"note.half_up","approximateX":821,"id":140780,"position_in_staff":"S2"},{"agnostic_symbol_type":"dot","approximateX":836,"id":140781,"position_in_staff":"S2"},{"agnostic_symbol_type":"note.quarter_up","approximateX":851,"id":140782,"position_in_staff":"S2"},{"agnostic_symbol_type":"note.half_up","approximateX":866,"id":140783,"position_in_staff":"S2"},{"agnostic_symbol_type":"accidental.flat","approximateX":881,"id":140784,"position_in_staff":"L3"},{"agnostic_symbol_type":"note.half_up","approximateX":896,"id":140785,"position_in_staff":"L3"},{"agnostic_symbol_type":"note.quarter_up","approximateX":911,"id":140786,"position_in_staff":"S2"},{"agnostic_symbol_type":"note.half_down","approximateX":926,"id":140787,"position_in_staff":"L4"},{"agnostic_symbol_type":"note.quarter_down","approximateX":941,"id":140788,"position_in_staff":"S3"},{"agnostic_symbol_type":"note.half_down","approximateX":956,"id":140789,"position_in_staff":"L5"},{"agnostic_symbol_type":"note.quarter_down","approximateX":971,"id":140790,"position_in_staff":"S4"},{"agnostic_symbol_type":"note.quarter_down","approximateX":986,"id":140791,"position_in_staff":"S4"},{"agnostic_symbol_type":"note.quarter_down","approximateX":1001,"id":140792,"position_in_staff":"L5"},{"agnostic_symbol_type":"dot","approximateX":1016,"id":140793,"position_in_staff":"S5"},{"agnostic_symbol_type":"note.eighth_down","approximateX":1031,"id":140794,"position_in_staff":"S4"},{"agnostic_symbol_type":"note.half_down","approximateX":1046,"id":140795,"position_in_staff":"L4"},{"agnostic_symbol_type":"rest.seminima","approximateX":1061,"id":140796,"position_in_staff":"L4"},{"agnostic_symbol_type":"note.quarter_down","approximateX":1076,"id":140797,"position_in_staff":"L5"},{"agnostic_symbol_type":"custos","approximateX":1091,"id":140798,"position_in_staff":"L5"}]},{"bounding_box":{"fromX":816,"toX":889,"fromY":193,"toY":213},"id":27706,"type":"lyrics"},{"bounding_box":{"fromX":653,"toX":804,"fromY":196,"toY":212},"id":27704,"type":"lyrics"},{"bounding_box":{"fromX":963,"toX":1033,"fromY":196,"toY":217},"id":27709,"type":"lyrics"},{"bounding_box":{"fromX":1063,"toX":1098,"fromY":196,"toY":216},"id":27710,"type":"lyrics"},{"bounding_box":{"fromX":891,"toX":952,"fromY":197,"toY":216},"id":27707,"type":"lyrics"},{"bounding_box":{"fromX":643,"toX":1119,"fromY":211,"toY":268},"id":27713,"type":"staff","symbols":[{"agnostic_symbol_type":"clef.G","approximateX":643,"id":140799,"position_in_staff":"L2"},{"agnostic_symbol_type":"note.quarter_down","approximateX":658,"id":140800,"position_in_staff":"L5"},{"agnostic_symbol_type":"note.half_down","approximateX":673,"id":140801,"position_in_staff":"S4"},{"agnostic_symbol_type":"note.quarter_down","approximateX":688,"id":140802,"position_in_staff":"L4"},{"agnostic_symbol_type":"note.half_down","approximateX":703,"id":140803,"position_in_staff":"S4"},{"agnostic_symbol_type":"note.half_down","approximateX":718,"id":140804,"position_in_staff":"L5"},{"agnostic_symbol_type":"note.quarter_down","approximateX":733,"id":140805,"position_in_staff":"L4"},{"agnostic_symbol_type":"note.half_down","approximateX":748,"id":140806,"position_in_staff":"L4"},{"agnostic_symbol_type":"note.quarter_up","approximateX":763,"id":140807,"position_in_staff":"S2"},{"agnostic_symbol_type":"note.quarter_up","approximateX":778,"id":140808,"position_in_staff":"S2"},{"agnostic_symbol_type":"dot","approximateX":793,"id":140809,"position_in_staff":"S2"},{"agnostic_symbol_type":"note.eighth_up","approximateX":808,"id":140810,"position_in_staff":"L3"},{"agnostic_symbol_type":"note.half_down","approximateX":823,"id":140811,"position_in_staff":"S3"},{"agnostic_symbol_type":"note.half_down","approximateX":838,"id":140812,"position_in_staff":"L4"},{"agnostic_symbol_type":"rest.seminima","approximateX":853,"id":140813,"position_in_staff":"L4"},{"agnostic_symbol_type":"note.quarter_down","approximateX":868,"id":140814,"position_in_staff":"S4"},{"agnostic_symbol_type":"note.quarter_down","approximateX":883,"id":140815,"position_in_staff":"L5"},{"agnostic_symbol_type":"note.quarter_down","approximateX":898,"id":140816,"position_in_staff":"S4"},{"agnostic_symbol_type":"note.quarter_down","approximateX":913,"id":140817,"position_in_staff":"L4"},{"agnostic_symbol_type":"note.quarter_down","approximateX":928,"id":140818,"position_in_staff":"S3"},{"agnostic_symbol_type":"note.half_down","approximateX":943,"id":140819,"position_in_staff":"L5"},{"agnostic_symbol_type":"note.whole","approximateX":958,"id":140820,"position_in_staff":"S4"},{"agnostic_symbol_type":"rest.half","approximateX":973,"id":140821,"position_in_staff":"L4"},{"agnostic_symbol_type":"rest.whole","approximateX":988,"id":140822,"position_in_staff":"L4"},{"agnostic_symbol_type":"rest.half","approximateX":1003,"id":140823,"position_in_staff":"L4"},{"agnostic_symbol_type":"note.half_down","approximateX":1018,"id":140824,"position_in_staff":"S4"},{"agnostic_symbol_type":"note.half_down","approximateX":1033,"id":140825,"position_in_staff":"S4"},{"agnostic_symbol_type":"note.half_down","approximateX":1048,"id":140826,"position_in_staff":"L4"},{"agnostic_symbol_type":"note.half_down","approximateX":1063,"id":140827,"position_in_staff":"S3"},{"agnostic_symbol_type":"custos","approximateX":1078,"id":140828,"position_in_staff":"L3"}]},{"bounding_box":{"fromX":656,"toX":812,"fromY":266,"toY":284},"id":27714,"type":"lyrics"},{"bounding_box":{"fromX":849,"toX":990,"fromY":266,"toY":286},"id":27715,"type":"lyrics"},{"bounding_box":{"fromX":1012,"toX":1105,"fromY":266,"toY":286},"id":27717,"type":"lyrics"},{"bounding_box":{"fromX":643,"toX":1119,"fromY":279,"toY":339},"id":27721,"type":"staff","symbols":[{"agnostic_symbol_type":"clef.G","approximateX":643,"id":140829,"position_in_staff":"L2"},{"agnostic_symbol_type":"note.half_up","approximateX":658,"id":140830,"position_in_staff":"L3"},{"agnostic_symbol_type":"note.whole","approximateX":673,"id":140831,"position_in_staff":"S2"},{"agnostic_symbol_type":"dot","approximateX":688,"id":140832,"position_in_staff":"S2"},{"agnostic_symbol_type":"rest.half","approximateX":703,"id":140833,"position_in_staff":"L3"},{"agnostic_symbol_type":"rest.whole","approximateX":718,"id":140834,"position_in_staff":"L4"},{"agnostic_symbol_type":"rest.half","approximateX":733,"id":140835,"position_in_staff":"L4"},{"agnostic_symbol_type":"note.half_down","approximateX":748,"id":140836,"position_in_staff":"L4"},{"agnostic_symbol_type":"note.half_down","approximateX":763,"id":140837,"position_in_staff":"L4"},{"agnostic_symbol_type":"accidental.sharp","approximateX":778,"id":140838,"position_in_staff":"S3"},{"agnostic_symbol_type":"note.half_down","approximateX":793,"id":140839,"position_in_staff":"S3"},{"agnostic_symbol_type":"note.quarter_down","approximateX":808,"id":140840,"position_in_staff":"L4"},{"agnostic_symbol_type":"note.quarter_down","approximateX":823,"id":140841,"position_in_staff":"S4"},{"agnostic_symbol_type":"note.quarter_down","approximateX":838,"id":140842,"position_in_staff":"L5"},{"agnostic_symbol_type":"note.quarter_down","approximateX":853,"id":140843,"position_in_staff":"L5"},{"agnostic_symbol_type":"note.quarter_down","approximateX":868,"id":140844,"position_in_staff":"S4"},{"agnostic_symbol_type":"note.quarter_down","approximateX":883,"id":140845,"position_in_staff":"L5"},{"agnostic_symbol_type":"note.half_down","approximateX":898,"id":140846,"position_in_staff":"S4"},{"agnostic_symbol_type":"note.whole","approximateX":913,"id":140847,"position_in_staff":"S3"},{"agnostic_symbol_type":"rest.whole","approximateX":928,"id":140848,"position_in_staff":"L4"},{"agnostic_symbol_type":"rest.seminima","approximateX":943,"id":140849,"position_in_staff":"L4"},{"agnostic_symbol_type":"note.quarter_down","approximateX":958,"id":140850,"position_in_staff":"L4"},{"agnostic_symbol_type":"note.quarter_down","approximateX":973,"id":140851,"position_in_staff":"S4"},{"agnostic_symbol_type":"dot","approximateX":988,"id":140852,"position_in_staff":"S4"},{"agnostic_symbol_type":"note.eighth_down","approximateX":1003,"id":140853,"position_in_staff":"L4"},{"agnostic_symbol_type":"note.quarter_down","approximateX":1018,"id":140854,"position_in_staff":"S3"},{"agnostic_symbol_type":"note.quarter_down","approximateX":1033,"id":140855,"position_in_staff":"S3"},{"agnostic_symbol_type":"note.half_down","approximateX":1048,"id":140856,"position_in_staff":"L4"},{"agnostic_symbol_type":"note.half_up","approximateX":1063,"id":140857,"position_in_staff":"L2"},{"agnostic_symbol_type":"note.half_down","approximateX":1078,"id":140858,"position_in_staff":"S3"},{"agnostic_symbol_type":"custos","approximateX":1093,"id":140859,"position_in_staff":"S3"}]},{"bounding_box":{"fromX":658,"toX":714,"fromY":336,"toY":354},"id":27723,"type":"lyrics"},{"bounding_box":{"fromX":730,"toX":945,"fromY":338,"toY":355},"id":27724,"type":"lyrics"},{"bounding_box":{"fromX":1027,"toX":1099,"fromY":338,"toY":355},"id":27726,"type":"lyrics"},{"bounding_box":{"fromX":951,"toX":1009,"fromY":339,"toY":358},"id":27725,"type":"lyrics"},{"bounding_box":{"fromX":644,"toX":1118,"fromY":355,"toY":409},"id":27729,"type":"staff","symbols":[{"agnostic_symbol_type":"clef.G","approximateX":644,"id":140860,"position_in_staff":"L2"},{"agnostic_symbol_type":"note.whole","approximateX":659,"id":140861,"position_in_staff":"S3"},{"agnostic_symbol_type":"rest.half","approximateX":674,"id":140862,"position_in_staff":"L4"},{"agnostic_symbol_type":"note.half_down","approximateX":689,"id":140863,"position_in_staff":"S4"},{"agnostic_symbol_type":"note.whole","approximateX":704,"id":140864,"position_in_staff":"S4"},{"agnostic_symbol_type":"rest.seminima","approximateX":719,"id":140865,"position_in_staff":"L4"},{"agnostic_symbol_type":"note.quarter_down","approximateX":734,"id":140866,"position_in_staff":"S4"},{"agnostic_symbol_type":"note.half_down","approximateX":749,"id":140867,"position_in_staff":"S4"},{"agnostic_symbol_type":"dot","approximateX":764,"id":140868,"position_in_staff":"S4"},{"agnostic_symbol_type":"note.quarter_down","approximateX":779,"id":140869,"position_in_staff":"L4"},{"agnostic_symbol_type":"note.half_down","approximateX":794,"id":140870,"position_in_staff":"L4"},{"agnostic_symbol_type":"note.quarter_up","approximateX":809,"id":140871,"position_in_staff":"L3"},{"agnostic_symbol_type":"note.half_up","approximateX":824,"id":140872,"position_in_staff":"L3"},{"agnostic_symbol_type":"note.quarter_up","approximateX":839,"id":140873,"position_in_staff":"L3"},{"agnostic_symbol_type":"note.quarter_down","approximateX":854,"id":140874,"position_in_staff":"S4"},{"agnostic_symbol_type":"dot","approximateX":869,"id":140875,"position_in_staff":"S4"},{"agnostic_symbol_type":"note.eighth_down","approximateX":884,"id":140876,"position_in_staff":"L4"},{"agnostic_symbol_type":"note.half_down","approximateX":899,"id":140877,"position_in_staff":"S3"},{"agnostic_symbol_type":"note.quarter_down","approximateX":914,"id":140878,"position_in_staff":"L4"},{"agnostic_symbol_type":"note.quarter_down","approximateX":929,"id":140879,"position_in_staff":"L4"},{"agnostic_symbol_type":"note.half_down","approximateX":944,"id":140880,"position_in_staff":"S4"},{"agnostic_symbol_type":"note.half_down","approximateX":959,"id":140881,"position_in_staff":"S4"},{"agnostic_symbol_type":"note.half_down","approximateX":974,"id":140882,"position_in_staff":"L4"},{"agnostic_symbol_type":"dot","approximateX":989,"id":140883,"position_in_staff":"S4"},{"agnostic_symbol_type":"note.quarter_down","approximateX":1004,"id":140884,"position_in_staff":"S3"},{"agnostic_symbol_type":"note.half_up","approximateX":1019,"id":140885,"position_in_staff":"L3"},{"agnostic_symbol_type":"note.whole","approximateX":1034,"id":140886,"position_in_staff":"S3"},{"agnostic_symbol_type":"rest.whole","approximateX":1049,"id":140887,"position_in_staff":"L4"},{"agnostic_symbol_type":"rest.breve","approximateX":1064,"id":140888,"position_in_staff":"L3"},{"agnostic_symbol_type":"rest.half","approximateX":1079,"id":140889,"position_in_staff":"L3"},{"agnostic_symbol_type":"custos","approximateX":1094,"id":140890,"position_in_staff":"S3"}]},{"bounding_box":{"fromX":659,"toX":886,"fromY":407,"toY":425},"id":27731,"type":"lyrics"},{"bounding_box":{"fromX":912,"toX":1056,"fromY":407,"toY":428},"id":27733,"type":"lyrics"},{"bounding_box":{"fromX":643,"toX":1118,"fromY":423,"toY":480},"id":27735,"type":"staff","symbols":[{"agnostic_symbol_type":"clef.G","approximateX":643,"id":140891,"position_in_staff":"L2"},{"agnostic_symbol_type":"note.quarter_down","approximateX":660,"id":140892,"position_in_staff":"S3"},{"agnostic_symbol_type":"note.quarter_down","approximateX":677,"id":140893,"position_in_staff":"S3"},{"agnostic_symbol_type":"note.half_down","approximateX":694,"id":140894,"position_in_staff":"L5"},{"agnostic_symbol_type":"note.quarter_down","approximateX":711,"id":140895,"position_in_staff":"S4"},{"agnostic_symbol_type":"note.quarter_down","approximateX":728,"id":140896,"position_in_staff":"L4"},{"agnostic_symbol_type":"note.quarter_down","approximateX":745,"id":140897,"position_in_staff":"S3"},{"agnostic_symbol_type":"note.half_down","approximateX":762,"id":140898,"position_in_staff":"S4"},{"agnostic_symbol_type":"note.quarter_down","approximateX":779,"id":140899,"position_in_staff":"S4"},{"agnostic_symbol_type":"note.half_down","approximateX":796,"id":140900,"position_in_staff":"S3"},{"agnostic_symbol_type":"note.quarter_down","approximateX":813,"id":140901,"position_in_staff":"S3"},{"agnostic_symbol_type":"note.quarter_down","approximateX":830,"id":140902,"position_in_staff":"L4"},{"agnostic_symbol_type":"note.half_down","approximateX":847,"id":140903,"position_in_staff":"S4"},{"agnostic_symbol_type":"note.half_down","approximateX":864,"id":140904,"position_in_staff":"S3"},{"agnostic_symbol_type":"dot","approximateX":881,"id":140905,"position_in_staff":"S3"},{"agnostic_symbol_type":"note.quarter_down","approximateX":898,"id":140906,"position_in_staff":"L4"},{"agnostic_symbol_type":"note.quarter_down","approximateX":915,"id":140907,"position_in_staff":"S4"},{"agnostic_symbol_type":"note.quarter_down","approximateX":932,"id":140908,"position_in_staff":"L5"},{"agnostic_symbol_type":"note.half_down","approximateX":949,"id":140909,"position_in_staff":"S5"},{"agnostic_symbol_type":"note.quarter_down","approximateX":966,"id":140910,"position_in_staff":"S4"},{"agnostic_symbol_type":"note.quarter_down","approximateX":983,"id":140911,"position_in_staff":"S4"},{"agnostic_symbol_type":"note.whole","approximateX":1000,"id":140912,"position_in_staff":"S4"},{"agnostic_symbol_type":"note.half_down","approximateX":1017,"id":140913,"position_in_staff":"S4"},{"agnostic_symbol_type":"note.quarter_down","approximateX":1034,"id":140914,"position_in_staff":"S3"},{"agnostic_symbol_type":"note.quarter_down","approximateX":1051,"id":140915,"position_in_staff":"S3"},{"agnostic_symbol_type":"note.half_down","approximateX":1068,"id":140916,"position_in_staff":"L5"},{"agnostic_symbol_type":"custos","approximateX":1085,"id":140917,"position_in_staff":"S4"}]},{"bounding_box":{"fromX":667,"toX":901,"fromY":476,"toY":496},"id":27738,"type":"lyrics"},{"bounding_box":{"fromX":960,"toX":1093,"fromY":479,"toY":499},"id":27739,"type":"lyrics"},{"bounding_box":{"fromX":641,"toX":1016,"fromY":492,"toY":549},"id":27740,"type":"staff","symbols":[{"agnostic_symbol_type":"clef.G","approximateX":641,"id":140918,"position_in_staff":"L2"},{"agnostic_symbol_type":"note.quarter_down","approximateX":657,"id":140919,"position_in_staff":"S4"},{"agnostic_symbol_type":"note.quarter_down","approximateX":673,"id":140920,"position_in_staff":"L4"},{"agnostic_symbol_type":"note.quarter_down","approximateX":689,"id":140921,"position_in_staff":"S3"},{"agnostic_symbol_type":"note.half_down","approximateX":705,"id":140922,"position_in_staff":"S4"},{"agnostic_symbol_type":"note.quarter_down","approximateX":721,"id":140923,"position_in_staff":"S4"},{"agnostic_symbol_type":"note.half_down","approximateX":737,"id":140924,"position_in_staff":"S3"},{"agnostic_symbol_type":"note.quarter_down","approximateX":753,"id":140925,"position_in_staff":"S3"},{"agnostic_symbol_type":"note.quarter_down","approximateX":769,"id":140926,"position_in_staff":"L4"},{"agnostic_symbol_type":"note.half_down","approximateX":785,"id":140927,"position_in_staff":"S4"},{"agnostic_symbol_type":"note.half_down","approximateX":801,"id":140928,"position_in_staff":"S3"},{"agnostic_symbol_type":"dot","approximateX":817,"id":140929,"position_in_staff":"S3"},{"agnostic_symbol_type":"note.quarter_down","approximateX":833,"id":140930,"position_in_staff":"L4"},{"agnostic_symbol_type":"note.quarter_down","approximateX":849,"id":140931,"position_in_staff":"S4"},{"agnostic_symbol_type":"note.quarter_down","approximateX":865,"id":140932,"position_in_staff":"L5"},{"agnostic_symbol_type":"note.half_down","approximateX":881,"id":140933,"position_in_staff":"S5"},{"agnostic_symbol_type":"note.quarter_down","approximateX":897,"id":140934,"position_in_staff":"S4"},{"agnostic_symbol_type":"note.quarter_down","approximateX":913,"id":140935,"position_in_staff":"S4"},{"agnostic_symbol_type":"note.whole","approximateX":929,"id":140936,"position_in_staff":"S4"},{"agnostic_symbol_type":"accidental.sharp","approximateX":945,"id":140937,"position_in_staff":"S3"},{"agnostic_symbol_type":"note.longa_down","approximateX":961,"id":140938,"position_in_staff":"S3"},{"agnostic_symbol_type":"verticalLine","approximateX":977,"id":140939,"position_in_staff":"L1"},{"agnostic_symbol_type":"verticalLine","approximateX":993,"id":140940,"position_in_staff":"L1"}]},{"bounding_box":{"fromX":1015,"toX":1120,"fromY":498,"toY":547},"id":27745,"type":"empty_staff"},{"bounding_box":{"fromX":664,"toX":855,"fromY":546,"toY":565},"id":27741,"type":"lyrics"},{"bounding_box":{"fromX":901,"toX":986,"fromY":546,"toY":569},"id":27742,"type":"lyrics"},{"bounding_box":{"fromX":643,"toX":1120,"fromY":567,"toY":621},"id":27747,"type":"empty_staff"},{"bounding_box":{"fromX":644,"toX":1120,"fromY":640,"toY":700},"id":27749,"type":"empty_staff"},{"bounding_box":{"fromX":951,"toX":1102,"fromY":697,"toY":716},"id":27750,"type":"text"}],"bounding_box":{"fromX":608,"toX":1153,"fromY":26,"toY":781},"id":3112}],"rotation":0,"id":3986,"collection":"Lauro Seco","url":"http://localhost:8182/iiif/2/correggio_mentreil:masters:correggio_mentreil_C.jpg/full/full/0/default.jpg"}