{
    "0": "note.half_up",
    "1": "note.longa_down",
    "2": "rest.seminima",
    "3": "note.breve",
    "4": "metersign.CcutZ",
    "5": "slur.end",
    "6": "note.quarter_up",
    "7": "metersign.Ct",
    "8": "fermata.below",
    "9": "note.doubleWholeStem_down",
    "10": "note.wholeBlack",
    "11": "signumCongruentiae",
    "12": "rest.whole",
    "13": "metersign.Ccut",
    "14": "rest.breve",
    "15": "note.quadrupleWholeStem_down",
    "16": "defect.inkBlot",
    "17": "note.beamedLeft2_up",
    "18": "clef.F",
    "19": "clef.Fpetrucci",
    "20": "defect.smudge",
    "21": "accidental.flat",
    "22": "verticalLine",
    "23": "dot",
    "24": "clef.C",
    "25": "note.tripleWholeStem_down",
    "26": "digit.4",
    "27": "note.whole",
    "28": "note.beamedLeft1_up",
    "29": "note.doubleWhole",
    "30": "note.beamedRight1_down",
    "31": "metersign.CZ",
    "32": "note.eighth_down",
    "33": "rest.longa2",
    "34": "note.eighth_up",
    "35": "clef.G",
    "36": "colon",
    "37": "note.quarter_down",
    "38": "note.beamedLeft1_down",
    "39": "note.longa_up",
    "40": "note.half_down",
    "41": "custos",
    "42": "note.beamedBoth1_down",
    "43": "slur.start",
    "44": "note.beamedLeft2_down",
    "45": "note.beamedRight2_down",
    "46": "note.tripleWholeStem_up",
    "47": "note.longaBlack_up",
    "48": "note.beamedRight2_up",
    "49": "note.longaBlack_down",
    "50": "note.beamedBoth1_up",
    "51": "rest.half",
    "52": "ligature",
    "53": "digit.3",
    "54": "note.doubleWholeStem_up",
    "55": "note.eighthVoid_up",
    "56": "accidental.natural",
    "57": "fermata.above",
    "58": "accidental.sharp",
    "59": "note.breveBlack",
    "60": "note.eighthVoid_down",
    "61": "note.beamedRight1_up"
}